[
  {
    "code": "7.00",
    "item": "Cable tray properly installed from ceiling"
  },
  {
    "code": "7.01",
    "item": "Cable tray properly installed using J bolts and splice kits"
  },
  {
    "code": "7.02",
    "item": "Unistrut materials installed as per work order and Rogers Standards"
  },
  {
    "code": "7.03",
    "item": "Unistrut properly anchored"
  },
  {
    "code": "7.04",
    "item": "Cable / ladder tray ground properly installed and connected to Master Ground Bar"
  },
  {
    "code": "7.05",
    "item": "Unistrut properly installed using J bolts, spring bolts, and splice kits"
  },
  {
    "code": "7.06",
    "item": "Cable tray lids secured (screwed and banded)"
  }
]
